{
  "version": 1,
  "base_track": "тљЏсЂ»сЂЊсЂ«тцЈсђЂТЂІсѓњсЂЎсѓІ",
  "base_artist": "РЅаME",
  "createdAt": "2026-03-23T11:13:21.055997Z",
  "candidates": [
    {
      "id": "lrclib_1",
      "source": "lrclib",
      "title": "тљЏсЂ»сЂЊсЂ«тцЈсђЂТЂІсѓњсЂЎсѓІ",
      "artist": "Not Equal Me",
      "has_synced": true,
      "path": "select/01_тљЏсЂ»сЂЊсЂ«тцЈсђЂТЂІсѓњсЂЎсѓІ_Not_Equal_Me.lrc"
    },
    {
      "id": "lrclib_2",
      "source": "lrclib",
      "title": "тљЏсЂ»сЂЊсЂ«тцЈсђЂТЂІсѓњсЂЎсѓІ",
      "artist": "РЅаME",
      "has_synced": true,
      "path": "select/02_тљЏсЂ»сЂЊсЂ«тцЈсђЂТЂІсѓњсЂЎсѓІ_РЅаME.lrc"
    },
    {
      "id": "petitlyrics_1",
      "source": "petitlyrics",
      "title": "тљЏсЂ»сЂЊсЂ«тцЈсђЂТЂІсѓњсЂЎсѓІ",
      "artist": "РЅаME",
      "has_synced": false,
      "path": "select/pl_01_тљЏсЂ»сЂЊсЂ«тцЈсђЂТЂІсѓњсЂЎсѓІ_РЅаME.txt"
    },
    {
      "id": "localdb_1",
      "source": "localdb",
      "title": "тљЏсЂ»сЂЊсЂ«тцЈсђЂТЂІсѓњсЂЎсѓІ",
      "artist": "РЅаME",
      "has_synced": true,
      "path": "select/localdb_01_тљЏсЂ»сЂЊсЂ«тцЈсђЂТЂІсѓњсЂЎсѓІ_РЅаME.lrc",
      "repo_name": "2wtb7QdR5kw"
    }
  ]
}